workforcesim/__init__.py
workforcesim/config.py
workforcesim/io_file_manager.py
workforcesim/wfs_app.py
workforcesim/wfs_behaviors.py
workforcesim/wfs_executor.py
workforcesim/wfs_personnel.py
workforcesim/wfs_records.py
workforcesim/wfs_utilities.py
workforcesim/wfs_visualizer.py
workforcesim-0.4.22.dist-info/LICENSE
workforcesim-0.4.22.dist-info/METADATA
workforcesim-0.4.22.dist-info/WHEEL
workforcesim-0.4.22.dist-info/top_level.txt
workforcesim-0.4.22.dist-info/RECORD
