Metadata-Version: 2.1
Name: workforcesim
Version: 0.4.22
Summary: Synaptans WorkforceSim is a free open-source web app for simulating the complex dynamics of a factory workforce – including workers’ daily job performance, personal interactions with their peers and supervisors, and attrition. The simulated activity is analyzed visually and outputted in a CSV file whose format is designed for use with predictive analytics packages like Comport_AI.
Home-page: https://github.com/NeuraXenetica/synaptans-workforcesim
Author: Matthew E. Gladden
Author-email: "Matthew E. Gladden" <matthew.gladden@neuraxenetica.com>
Maintainer: Matthew E. Gladden
Project-URL: Homepage, https://github.com/NeuraXenetica/synaptans-workforcesim
Project-URL: Bug Tracker, https://github.com/NeuraXenetica/synaptans-workforcesim/issues
Classifier: Programming Language :: Python :: 3
Classifier: License :: OSI Approved :: GNU General Public License v3 (GPLv3)
Classifier: Operating System :: Microsoft :: Windows
Requires-Python: >=3.9
License-File: LICENSE
Requires-Dist: numpy
Requires-Dist: pandas
Requires-Dist: fastapi
Requires-Dist: uvicorn
Requires-Dist: jinja2
Requires-Dist: matplotlib
Requires-Dist: python-multipart
Requires-Dist: seaborn
